LICENCE.txt
README.md
setup.py
LinearRegressionLab/__init__.py
LinearRegressionLab/linear_regression_model.py
LinearRegressionLab.egg-info/PKG-INFO
LinearRegressionLab.egg-info/SOURCES.txt
LinearRegressionLab.egg-info/dependency_links.txt
LinearRegressionLab.egg-info/requires.txt
LinearRegressionLab.egg-info/top_level.txt