Metadata-Version: 2.1
Name: LinearRegressionLab
Version: 1.0.2
Summary: Package doing linear regression
Home-page: http://pypi.python.org/pypi/LinearRegressionLab/
Author: Guerinik Abderrahmane
Author-email: ca.guerinik@esi-sba.dz
License: LICENSE.txt
License-File: LICENCE.txt
Requires-Dist: LinearRegressionLab
